GraduateComputerGraphicsNyuCsciGa2270001/README.md
GraduateComputerGraphicsNyuCsciGa2270001/__init__.py
GraduateComputerGraphicsNyuCsciGa2270001/__main__.py
GraduateComputerGraphicsNyuCsciGa2270001/file.epub
GraduateComputerGraphicsNyuCsciGa2270001/index.html
GraduateComputerGraphicsNyuCsciGa2270001/css/__init__.py
GraduateComputerGraphicsNyuCsciGa2270001/css/annotations.css
GraduateComputerGraphicsNyuCsciGa2270001/css/main.css
GraduateComputerGraphicsNyuCsciGa2270001/css/normalize.css
GraduateComputerGraphicsNyuCsciGa2270001/css/popup.css
GraduateComputerGraphicsNyuCsciGa2270001/font/__init__.py
GraduateComputerGraphicsNyuCsciGa2270001/font/fontello.eot
GraduateComputerGraphicsNyuCsciGa2270001/font/fontello.svg
GraduateComputerGraphicsNyuCsciGa2270001/font/fontello.ttf
GraduateComputerGraphicsNyuCsciGa2270001/font/fontello.woff
GraduateComputerGraphicsNyuCsciGa2270001/img/__init__.py
GraduateComputerGraphicsNyuCsciGa2270001/img/annotator-glyph-sprite.png
GraduateComputerGraphicsNyuCsciGa2270001/img/annotator-icon-sprite.png
GraduateComputerGraphicsNyuCsciGa2270001/img/apple-touch-icon.png
GraduateComputerGraphicsNyuCsciGa2270001/img/cancelfullscreen.png
GraduateComputerGraphicsNyuCsciGa2270001/img/close.png
GraduateComputerGraphicsNyuCsciGa2270001/img/fullscreen.png
GraduateComputerGraphicsNyuCsciGa2270001/img/loader.gif
GraduateComputerGraphicsNyuCsciGa2270001/img/menu-icon.png
GraduateComputerGraphicsNyuCsciGa2270001/img/save.png
GraduateComputerGraphicsNyuCsciGa2270001/img/saved.png
GraduateComputerGraphicsNyuCsciGa2270001/img/settings-s.png
GraduateComputerGraphicsNyuCsciGa2270001/img/settings.png
GraduateComputerGraphicsNyuCsciGa2270001/img/star.png
GraduateComputerGraphicsNyuCsciGa2270001/js/__init__.py
GraduateComputerGraphicsNyuCsciGa2270001/js/epub.js
GraduateComputerGraphicsNyuCsciGa2270001/js/epub.min.js
GraduateComputerGraphicsNyuCsciGa2270001/js/epub.min.map
GraduateComputerGraphicsNyuCsciGa2270001/js/hooks.min.js
graduate_computer_graphics_nyu_csci_ga_2270_001-2024.3.2.0.dist-info/METADATA
graduate_computer_graphics_nyu_csci_ga_2270_001-2024.3.2.0.dist-info/WHEEL
graduate_computer_graphics_nyu_csci_ga_2270_001-2024.3.2.0.dist-info/entry_points.txt
graduate_computer_graphics_nyu_csci_ga_2270_001-2024.3.2.0.dist-info/top_level.txt
graduate_computer_graphics_nyu_csci_ga_2270_001-2024.3.2.0.dist-info/RECORD
